chatvat/__init__.py
chatvat/bot_template/.dockerignore
chatvat/bot_template/Dockerfile
chatvat/bot_template/docker-compose.yml
chatvat/bot_template/requirements.txt
chatvat/bot_template/src/__init__.py
chatvat/bot_template/src/main.py
chatvat/builder.py
chatvat/config_loader.py
chatvat/config_schema.py
chatvat/connectors/crawler.py
chatvat/connectors/loader.py
chatvat/constants.py
chatvat/core/engine.py
chatvat/core/ingestor.py
chatvat/core/vector.py
chatvat/main.py
chatvat/utils/__init__.py
chatvat/utils/logger.py
chatvat-0.1.12.dist-info/LICENSE
chatvat-0.1.12.dist-info/METADATA
chatvat-0.1.12.dist-info/WHEEL
chatvat-0.1.12.dist-info/entry_points.txt
chatvat-0.1.12.dist-info/RECORD
