Metadata-Version: 2.3
Name: chatvat
Version: 0.1.12
Summary: The Universal RAG Chatbot Factory. Zero-dependency AI deployments.
License: Apache-2.0
Author: Madhav Kapila
Author-email: smartatk04@gmail.com
Requires-Python: >=3.11,<4.0
Classifier: License :: OSI Approved :: Apache Software License
Classifier: Operating System :: OS Independent
Classifier: Programming Language :: Python :: 3
Classifier: Programming Language :: Python :: 3.11
Classifier: Programming Language :: Python :: 3.12
Classifier: Programming Language :: Python :: 3.13
Classifier: Topic :: Scientific/Engineering :: Artificial Intelligence
Classifier: Topic :: Software Development :: Build Tools
Provides-Extra: engine
Requires-Dist: beautifulsoup4 (>=4.12.0,<5.0.0) ; extra == "engine"
Requires-Dist: chromadb (>=0.5.0,<0.6.0) ; extra == "engine"
Requires-Dist: crawl4ai (>=0.4.0,<0.5.0) ; extra == "engine"
Requires-Dist: fastapi (>=0.109.0,<0.110.0) ; extra == "engine"
Requires-Dist: langchain (>=0.3.0,<0.4.0) ; extra == "engine"
Requires-Dist: langchain-chroma (>=0.2.0,<0.3.0) ; extra == "engine"
Requires-Dist: langchain-community (>=0.3.0,<0.4.0) ; extra == "engine"
Requires-Dist: langchain-groq (>=0.2.0,<0.3.0) ; extra == "engine"
Requires-Dist: langchain-huggingface (>=0.1.0,<0.2.0) ; extra == "engine"
Requires-Dist: langchain-openai (>=0.2.0,<0.3.0) ; extra == "engine"
Requires-Dist: openai (>=1.10.0,<2.0.0) ; extra == "engine"
Requires-Dist: playwright (>=1.40.0,<2.0.0) ; extra == "engine"
Requires-Dist: pydantic (>=2.0.0,<3.0.0)
Requires-Dist: pyfiglet (>=1.0.2,<2.0.0)
Requires-Dist: pypdf (>=4.0.0,<5.0.0) ; extra == "engine"
Requires-Dist: python-dotenv (>=1.0.0,<2.0.0)
Requires-Dist: requests (>=2.31.0,<3.0.0)
Requires-Dist: rich (>=13.7.0,<14.0.0)
Requires-Dist: tiktoken (>=0.7.0,<0.8.0) ; extra == "engine"
Requires-Dist: torch (>=2.2.0,<3.0.0) ; extra == "engine"
Requires-Dist: typer (>=0.12.3)
Requires-Dist: uvicorn[standard] (>=0.27.0,<0.28.0) ; extra == "engine"
Project-URL: Homepage, https://github.com/madhavkapila
Project-URL: Repository, https://github.com/madhavkapila/ChatVat.git
